RSSreddit/__init__.py
RSSreddit/base.py
RSSreddit/rssreddit.py
RSSreddit/util.py
RSSreddit-0.1.0.dist-info/DESCRIPTION.rst
RSSreddit-0.1.0.dist-info/METADATA
RSSreddit-0.1.0.dist-info/RECORD
RSSreddit-0.1.0.dist-info/WHEEL
RSSreddit-0.1.0.dist-info/metadata.json
RSSreddit-0.1.0.dist-info/top_level.txt
