Metadata-Version: 2.0
Name: RSSreddit
Version: 0.1.0
Summary: Reddits RSS in JSON
Home-page: https://github.com/algogator/RSSreddit
Author: Algogator
Author-email: algogator@gmail.com
License: MIT license
Keywords: RSSreddit
Platform: UNKNOWN
Classifier: Development Status :: 2 - Pre-Alpha
Classifier: Intended Audience :: Developers
Classifier: License :: OSI Approved :: MIT License
Classifier: Natural Language :: English
Classifier: Programming Language :: Python :: 2
Classifier: Programming Language :: Python :: 2.6
Classifier: Programming Language :: Python :: 2.7
Classifier: Programming Language :: Python :: 3
Classifier: Programming Language :: Python :: 3.3
Classifier: Programming Language :: Python :: 3.4
Classifier: Programming Language :: Python :: 3.5
